Workbook

Sheet COVER
D6: Financial analysis of OLO Inc.
D15: By Cristian Vasquez
D19: Income Statement, Balance Sheet & Cash Flow Analysis Forecasting and DCF Valuation

Sheet Income Statement
U2: Dollar change and percent change
F3: VERTICAL ANALYSIS | U3: (HORIZONTAL ANALYSIS)
B4: Year Ended December 31, | E4: 2024 | F4: VA | H4: 2023 | I4: VA | K4: 2022 | L4: VA | N4: 2021 | O4: VA | Q4: 2020 | R4: VA | U4: 24/23 | V4: 23/22 | W4: 22/21 | X4: 21/20 | Y4: Mean | Z4: Median
B6: Revenue:
B9: Total revenue | E9: 284,938 | F9: =E9/E$9 -> 1 | H9: 228,289 | I9: =H9/H$9 -> 1 | K9: 185,404 | L9: =K9/K$9 -> 1 | N9: 149,368 | O9: =N9/N$9 -> 1 | Q9: 98,424 | R9: =Q9/Q$9 -> 1 | U9: =E9-H9 -> 56649 | V9: =H9-K9 -> 42885 | W9: =K9-N9 -> 36036 | X9: =N9-Q9 -> 50944 | Y9: =(X9+W9+V9+U9)/4 -> 46628.5 | Z9: =(W9+V9)/2 -> 39460.5
U10: =U9/H9 -> 0.24814599 | V10: =V9/K9 -> 0.23130569 | W10: =W9/N9 -> 0.24125649 | X10: =X9/Q9 -> 0.51759733 | Y10: =(X10+W10+V10+U10)/4 -> 0.30957638 | Z10: =(W10+U10)/2 -> 0.24470124
B12: Total cost of rev | E12: 128,515 | F12: =E12/E$9 -> 0.45102794 | H12: =H9-H15 -> 89323 | I12: =H12/H$9 -> 0.39127159 | K12: =K9-K15 -> 58466 | L12: =K12/K$9 -> 0.31534379 | N12: 30,380 | O12: =N12/N$9 -> 0.20339028 | Q12: 18,668 | R12: =Q12/Q$9 -> 0.18966919 | U12: =E12-H12 -> 39192 | V12: =H12-K12 -> 30857 | W12: =K12-N12 -> 28086 | X12: =N12-Q12 -> 11712 | Y12: =(U12+V12+W12+X12)/4 -> 27461.75 | Z12: =(V12+W12)/2 -> 29471.5
U13: =U12/H12 -> 0.43876717 | V13: =V12/K12 -> 0.52777683 | W13: =W12/N12 -> 0.9244898 | X13: =X12/Q12 -> 0.62738376
B15: Gross Profit | E15: 156,423 | F15: =E15/E$9 -> 0.54897206 | H15: 138,966 | I15: =H15/H$9 -> 0.60872841 | K15: 126,938 | L15: =K15/K$9 -> 0.68465621 | N15: 117,995 | O15: =N15/N$9 -> 0.78996171 | Q15: 79,756 | R15: =Q15/Q$9 -> 0.81033081 | U15: =E15-H15 -> 17457 | V15: =H15-K15 -> 12028 | W15: =K15-N15 -> 8943 | X15: =N15-Q15 -> 38239 | Y15: =(X15+W15+V15+U15)/4 -> 19166.75 | Z15: =(W15+V15)/2 -> 10485.5
B16: Operating expenses: | U16: =U15/H15 -> 0.12562066 | V16: =V15/K15 -> 0.09475492 | W16: =W15/N15 -> 0.075791347 | X16: =X15/Q15 -> 0.47944982 | Y16: =(X16+W16+V16+U16)/4 -> 0.19390419 | Z16: =(W16+V16)/2 -> 0.085273133
B18: Total operating expenses | E18: 175,564 | F18: =E18/E$9 -> 0.61614807 | H18: 214,050 | I18: =H18/H$9 -> 0.93762731 | K18: 179,557 | L18: =K18/K$9 -> 0.96846346 | N18: 146,514 | O18: =N18/N$9 -> 0.98089283 | Q18: 63,661 | R18: =Q18/Q$9 -> 0.64680363 | U18: =E18-H18 -> -38486 | V18: =H18-K18 -> 34493 | W18: =K18-N18 -> 33043 | X18: =N18-Q18 -> 82853 | Y18: =(X18+W18+V18+U18)/4 -> 27975.75 | Z18: =(W18+V18)/2 -> 33768
U20: =U18/H18 -> -0.17979911 | V20: =V18/K18 -> 0.19210056 | W20: =W18/N18 -> 0.22552794 | X20: =X18/Q18 -> 1.3014719 | Y20: =(U20+X20+W20+V20)/4 -> 0.38482531 | Z20: =(W20+V20)/2 -> 0.20881425
B21: Net (loss) income and comprehensive (loss) income | E21: (85,300) | F21: =E21/E$9 -> -0.29936337 | H21: (58,049) | I21: =H21/H$9 -> -0.25427857 | K21: (45,968) | L21: =K21/K$9 -> -0.24793424 | N21: (42,273) | O21: =N21/N$9 -> -0.28301243 | Q21: 3,063 | R21: =Q21/Q$9 -> 0.031120458
U22: =E21-H21 -> -27251 | V22: =H21-K21 -> -12081 | W22: =K21-N21 -> -3695 | X22: =N21-Q21 -> -45336 | Y22: =(X22+W22+V22+U22)/4 -> -22090.75 | Z22: =(V22+U22)/2 -> -19666
U23: =U22/H21 -> 0.46944822 | V23: =V22/K21 -> 0.26281326 | W23: =W22/N21 -> 0.087408038 | X23: =X22/Q21 -> -14.801175 | Y23: =(W23+U23+V23+X23)/4 -> -3.4953764 | Z23: =(W23+V23)/2 -> 0.17511065
B26: RATIO ANALYSIS
B28: GPM | E28: =E15/E9 -> 0.54897206 | H28: =H15/H9 -> 0.60872841 | K28: =K15/K9 -> 0.68465621 | N28: =N15/N9 -> 0.78996171 | Q28: =Q15/Q9 -> 0.81033081
B30: OPM | E30: =(E15-E12)/E9 -> 0.097944114 | H30: =(H15-H12)/H9 -> 0.21745682 | K30: =(K15-K12)/K9 -> 0.36931242 | N30: =(N15-N12)/N9 -> 0.58657142 | Q30: =(Q15-Q12)/Q9 -> 0.62066163
B32: Net Margin | E32: =E21/E9 -> -0.29936337 | H32: =H21/H9 -> -0.25427857 | K32: =K21/K9 -> -0.24793424 | N32: =N21/N9 -> -0.28301243 | Q32: =Q21/Q9 -> 0.031120458

Sheet Balance Sheet
B2: Balance Sheet
D3: As of decmeber 30th,
B4: Dates | F4: 2024 | H4: 2023 | J4: 2022 | L4: 2021 | N4: 2020
B6: Assets
B8: As of December 31, 2020
B9: ASSETS
B10: Current assets: | F10: 448321 | H10: 450737 | J10: 511774 | L10: 565617 | N10: 125244
B12: Cash and cash equivalents | F12: 286757 | H12: 278218 | J12: 350073 | L12: 514440 | N12: 75756
B14: Total assets | F14: 754776 | H14: 742819 | J14: 775562 | L14: 755876 | N14: 134424
B15: LIABILITIES, REDEEMABLE CONVERTIBLE PREFERRED STOCK AND STOCKHOLDERS’ EQUITY (DEFICIT)
B16: Current liabilities: | F16: 59594 | H16: 77214 | J16: 60417 | L16: 48769 | N16: 72002
B18: Total liabilities | F18: 71553 | H18: 91348 | J18: 77946 | L18: 54126 | N18: 75168
B20: Total stockholders’ equity (deficit) | F20: 683223 | H20: 651471 | J20: 697616 | L20: 701750 | N20: -52481
B22: Total liabilities, redeemable convertible preferred stock and stockholders’ equity (deficit) | F22: 754776 | H22: 742819 | J22: =J18+J20 -> 775562 | L22: 755876 | N22: 134424
B26: Current ratio | F26: =F10/F16 -> 7.5229218 | H26: =H10/H16 -> 5.8375036 | J26: =J10/J16 -> 8.4706953 | L26: =L10/L16 -> 11.59788 | N26: =N10/N16 -> 1.7394517
B28: Debt to equity | F28: =F18/F20 -> 0.10472862 | H28: =H18/H20 -> 0.14021806 | J28: =J18/J20 -> 0.11173196 | L28: =L18/L20 -> 0.077130032 | N28: =N18/N20 -> -1.4322898
B30: Debt ratio | F30: =F18/F14 -> 0.094800312 | H30: =H18/H14 -> 0.12297478 | J30: =J18/J14 -> 0.1005026 | L30: =L18/L14 -> 0.071606983 | N30: =N18/N14 -> 0.55918586
B35: Asset turnover | F35: ='Income Statement'!E9/F14 -> 0.37751333 | H35: ='Income Statement'!H9/H10 -> 0.50647939 | J35: ='Income Statement'!K9/J14 -> 0.23905761 | L35: ='Income Statement'!N9/L14 -> 0.19760913 | N35: ='Income Statement'!Q9/N14 -> 0.73219068
B37: ROA | F37: ='Income Statement'!E21/F14 -> -0.11301366 | H37: ='Income Statement'!H21/H14 -> -0.078146897 | J37: ='Income Statement'!K21/J14 -> -0.059270568 | L37: ='Income Statement'!N21/L14 -> -0.05592584 | N37: ='Income Statement'!Q21/N14 -> 0.02278611
B71: Total Assets
B73: Liabilities
B75: Shareholders' Funds
B76: Equity Share Capital
B77: Retained Earnings
B79: Long Term Debt
B81: Current Liabilities
B82: Accounts Payables
B84: Total Liabilities
B85: Check
B87: Current Ratio
B88: Industry Average - GCC
... B101: Inventory Days
E104: =SUM(E12:E12)-E81 -> 0 | F104: =SUM(F12:F12)-F81 -> 286757 | H104: =SUM(L12:L12)-H81 -> 514440 | J104: =SUM(N12:N12)-J81 -> 75756
B105: WC | D105: =SUM(D12:D12)-D82 -> 0
E106: =-(E78-#REF!) -> #REF! | F106: =-(F78-#REF!) -> #REF! | H106: =-(H78-#REF!) -> #REF! | J106: =-(J78-#REF!) -> #REF!
B107: Net Debt | D107: =-(D79-#REF!) -> #REF!

Sheet Cash Flow
B2: Cash Flow Statement
D4: 2024 | E4: 2023 | F4: 2022 | G4: 2021 | H4: 2020
B5: Operating activities
B6: Net cash provided by operating activities | D6: 39,688 | E6: (6,568) | F6: 2,344 | G6: 16,253 | H6: 20,768
B7: Investing activities
B8: Net cash used in investing activities | D8: (16,872) | E8: (19,490) | F8: (158,483) | G8: (77,072) | H8: (1,273)
B9: Financing activities
B10: Net cash provided by financing activities | D10: -14277 | E10: -45797 | F10: 8233 | G10: 499508 | H10: 45326
B12: Cash and cash equivalents, end of year | D12: 278218 | E12: 278218 | F12: 350073 | G12: 514445 | H12: 0
D56: `

Sheet DCF
A1: Juice Co.
A2: Discounted Cash Flow
A4: ='Balance Sheet'!B4 -> Dates
D5: 1 | E5: 2 | F5: 3 | G5: =+F5+1 -> 4 | H5: =+G5+1 -> 5 | I5: =+H5+1 -> 6 | J5: =+I5+1 -> 7 | K5: =+J5+1 -> 8 | L5: =+K5+1 -> 9 | M5: =+L5+1 -> 10
D6: 2024 | F6: 2023 | H6: 2022 | J6: 2021 | L6: 2020
A8: EBITDA | D8: -4705 | F8: -64795 | H8: -45644 | J8: -26361 | L8: 16095
A10: D&A | D10: 14436 | F10: 10289 | H10: 6020 | J10: 1615 | L10: 673
A12: EBIT | D12: -19141 | F12: 6020 | H12: 51664 | J12: -27976 | L12: 16768
A14: Taxes | D14: 0 | E14: 0 | F14: 0 | G14: 0 | H14: 0 | I14: 0 | J14: 0 | K14: 0 | L14: 0 | M14: 0
A16: Capex | D16: ='Cash Flow'!D8 -> (16,872) | F16: ='Cash Flow'!E8 -> (19,490) | H16: ='Cash Flow'!F8 -> (158,483) | J16: ='Cash Flow'!G8 -> (77,072) | L16: ='Cash Flow'!H8 -> (1,273)
D18: =('Balance Sheet'!F10 -'Balance Sheet'!F12)-'Balance Sheet'!F16 -> 101970 | F18: =('Balance Sheet'!H10 -'Balance Sheet'!H12)-'Balance Sheet'!H16 -> 95305 | H18: =('Balance Sheet'!J10 -'Balance Sheet'!J12)-'Balance Sheet'!J16 -> 101284 | J18: =('Balance Sheet'!L10 -'Balance Sheet'!L12)-'Balance Sheet'!L16 -> 2408 | L18: =Q18 -> -22514 | N18: Starting amount | Q18: =('Balance Sheet'!N10 -'Balance Sheet'!N12)-'Balance Sheet'!N16 -> -22514
D19: =D18-F18 -> 6665 | F19: =F18-H18 -> -5979 | H19: =H18-J18 -> 98876 | J19: =J18-L18 -> 24922
A22: FCF | D22: {=SUM(D8:D16+D19)} -> 33703 | F22: {=SUM(F8:F12+F16+F19)} -> -175831 | H22: =SUM(H8+H10+H12+H16+H19) -> -47567 | J22: =J8+J10+J12+J16+J19 -> -104872 | L22: =L8+L10+L12+L16+L18 -> 9749
A23: Factor
A24: Discounted FCF
A26: WACC | C26: ='WACC Calculation'!C11 -> 0.13245
A27: PGR | C27: 0.025
A29: Year of Forecast | C29: 1 | D29: 2 | E29: 3 | F29: 4 | G29: 5
A30: Terminal value | C30: =1/(1+C26) -> 0.88304119 | D30: =1/(1+C26)^2 -> 0.77976175 | E30: =(1/(1+C26))^3 -> 0.68856175 | F30: =1/(1+C26)^4 -> 0.60802839 | G30: =1/(1+C26)^5 -> 0.53691411
A31: Discounted TV | C31: =C30*0.54 -> 0.47684224 | D31: =D30*0.54 -> 0.42107135 | E31: =E30*0.54 -> 0.37182334 | F31: =F30*0.54 -> 0.32833533 | G31: =G30*0.54 -> 0.28993362
A33: PV of CF | C33: =SUM(C40:G40) -> 126200.17
A35: TV calculation | C35: =(G39*1.03)/(0.1) -> 392758.07
A36: DTV Calcualtion | C36: =C35*G30 -> 210877.35
A37: Forecast
A39: FCF | C39: =33703*(1+C27) -> 34545.575 | D39: =C39*(1+C27) -> 35409.214 | E39: =D39*(1+C27) -> 36294.445 | F39: =E39*(1+C27) -> 37201.806 | G39: =F39*(1+C27) -> 38131.851
A40: DFCF | C40: =C39*C30 -> 30505.166 | D40: =D39*D30 -> 27610.751 | E40: =E39*E30 -> 24990.966 | F40: =F39*F30 -> 22619.754 | G40: =G39*G30 -> 20473.529
A42: EV | C42: =C33+C36 -> 337077.51
A44: Equity Value | C44: =C42+'Balance Sheet'!F12 -> 623834.51
A46: Price per share | C46: 3.96

Sheet WACC Calculation
B2: Target capital structure
B4: Debt | C4: 0
B5: 10y treasury | C5: 0.045
B6: Cost of Equity | C6: =(C5+1.59*5.5%) -> 0.13245
B7: Tax rate | C7: 0.21
B8: pre-tax Cost of Debt | C8: 0
B9: Post tax cost of debt | C9: 0
B11: WACC | C11: =C6 -> 0.13245

Sheet Football Field
C4: FY1 | D4: =+DCF!$D$8 -> -4705
C6: Trading Comps FY+1 EBITDA | D6: =+G6*J6 -> -47050 | E6: =+F6-D6 -> -9410 | F6: =+H6*J6 -> -56460 | G6: 10 | H6: 12 | I6: FY+1 EBITDA | J6: =+DCF!D8 -> -4705
C7: DCF | D7: 550 | E7: =+F7-D7 -> 200 | F7: 750 | G7: 10-12% WACC, 1.5-2.5% PGR
C8: FCFE | D8: 510 | E8: =+F8-D8 -> 70 | F8: 580 | G8: 14-16% CoE, 1.5-2.5% PGR
C9: LBO (5 year exit) | D9: 440 | E9: =+F9-D9 -> 50 | F9: 490 | G9: 5 Year exit, Exit Multiple = 12x, Returns: 20-25%
C14: =+C9 -> LBO (5 year exit) | D14: =+D9 -> 440 | E14: =+E9 -> 50
C15: =+C8 -> FCFE | D15: =+D8 -> 510 | E15: =+E8 -> 70
C16: =+C7 -> DCF | D16: =+D7 -> 550 | E16: =+E7 -> 200
C17: =+C6 -> Trading Comps FY+1 EBITDA | D17: =+D6 -> -47050 | E17: =+E6 -> -9410
C21: Trading Comps FY+1 EBITDA | D21: =D6/$D$4 -> 10 | F21: =F6/$D$4 -> 12 | J21: 400 | K21: 750
C22: DCF | D22: =D7/$D$4 -> -0.11689692 | F22: =F7/$D$4 -> -0.15940489 | J22: =+J21/DCF!$D$8 -> -0.08501594 | K22: =+K21/DCF!$D$8 -> -0.15940489
C23: FCFE | D23: =D8/$D$4 -> -0.10839532 | F23: =F8/$D$4 -> -0.12327311
C24: LBO (5 year exit) | D24: =D9/$D$4 -> -0.093517535 | F24: =F9/$D$4 -> -0.10414453

Sheet Charts
C2: 300 | D2: =+C2+100 -> 400 | E2: =+D2+100 -> 500 | F2: =+E2+100 -> 600 | G2: =+F2+100 -> 700 | H2: =+G2+100 -> 800
A3: FY1 | B3: =+DCF!$D$8 -> -4705 | C3: =C2/$B$3 -> -0.063761955 | D3: =D2/$B$3 -> -0.08501594 | E3: =E2/$B$3 -> -0.10626993 | F3: =F2/$B$3 -> -0.12752391 | G3: =G2/$B$3 -> -0.1487779 | H3: =H2/$B$3 -> -0.17003188
A4: FY2 | B4: =+DCF!$E$8 -> 0 | C4: =C2/$B$4 -> #DIV/0! | D4: =D2/$B$4 -> #DIV/0! | E4: =E2/$B$4 -> #DIV/0! | F4: =F2/$B$4 -> #DIV/0! | G4: =G2/$B$4 -> #DIV/0! | H4: =H2/$B$4 -> #DIV/0!
